cuadra_ai_sdk-1.0.4.dist-info/licenses/LICENSE
cuadraai/__init__.py
cuadraai/api_helper.py
cuadraai/configuration.py
cuadraai/cuadraai_client.py
cuadraai/controllers/__init__.py
cuadraai/controllers/base_controller.py
cuadraai/controllers/chat_controller.py
cuadraai/controllers/embeds_controller.py
cuadraai/controllers/models_controller.py
cuadraai/controllers/oauth_authorization_controller.py
cuadraai/controllers/usage_controller.py
cuadraai/exceptions/__init__.py
cuadraai/exceptions/api_exception.py
cuadraai/exceptions/error_response_exception.py
cuadraai/exceptions/oauth_provider_exception.py
cuadraai/http/__init__.py
cuadraai/http/api_response.py
cuadraai/http/http_call_back.py
cuadraai/http/http_method_enum.py
cuadraai/http/http_request.py
cuadraai/http/http_response.py
cuadraai/http/auth/__init__.py
cuadraai/http/auth/oauth_2.py
cuadraai/logging/__init__.py
cuadraai/logging/sdk_logger.py
cuadraai/logging/configuration/__init__.py
cuadraai/logging/configuration/api_logging_configuration.py
cuadraai/models/__init__.py
cuadraai/models/chat.py
cuadraai/models/chat_response_ex.py
cuadraai/models/content_ex.py
cuadraai/models/embed.py
cuadraai/models/embed_response_ex.py
cuadraai/models/inline_data_ex.py
cuadraai/models/model_ex.py
cuadraai/models/oauth_provider_error.py
cuadraai/models/oauth_token.py
cuadraai/models/paginated_response_ex_list_model_ex.py
cuadraai/models/tokens_ex.py
cuadraai/models/total_usage_ex.py
cuadraai/models/usage_calculation_ex.py
cuadraai/models/usage_ex.py
cuadraai/utilities/__init__.py
cuadraai/utilities/file_wrapper.py
cuadra_ai_sdk-1.0.4.dist-info/METADATA
cuadra_ai_sdk-1.0.4.dist-info/WHEEL
cuadra_ai_sdk-1.0.4.dist-info/top_level.txt
cuadra_ai_sdk-1.0.4.dist-info/RECORD
