Metadata-Version: 2.4
Name: cuadra-ai-sdk
Version: 1.0.4
Summary: Build AI agents with your own data, accelerate time-to-value, and create solutions as unique as your business.
Author-email: Cuadra AI <dan@cuadra.ai>
Project-URL: Documentation, https://docs.cuadra.ai/
Keywords: AI,CuadraAI,model,embed
Requires-Python: >=3.7
License-File: LICENSE
Requires-Dist: apimatic-core>=0.2.20,~=0.2.0
Requires-Dist: apimatic-core-interfaces>=0.1.5,~=0.1.0
Requires-Dist: apimatic-requests-client-adapter>=0.1.6,~=0.1.0
Provides-Extra: testutils
Requires-Dist: pytest>=7.2.2; extra == "testutils"
Dynamic: license-file
